pikpak_cli/__init__.py
pikpak_cli/ant.py
pikpak_cli/main.py
pikpak_cli-0.1.0.dist-info/LICENSE
pikpak_cli-0.1.0.dist-info/METADATA
pikpak_cli-0.1.0.dist-info/WHEEL
pikpak_cli-0.1.0.dist-info/entry_points.txt
pikpak_cli-0.1.0.dist-info/RECORD
