Metadata-Version: 2.1
Name: pikpak-cli
Version: 0.1.0
Summary: A pikpak command line client
Home-page: https://github.com/strongbugman/pikpak_cli
License: MIT
Author: strongbugman
Author-email: strongbugman@gmail.com
Requires-Python: >=3.8,<4.0
Classifier: Environment :: Console
Classifier: License :: OSI Approved :: MIT License
Classifier: Programming Language :: Python :: 3
Classifier: Programming Language :: Python :: 3.8
Classifier: Programming Language :: Python :: 3.9
Classifier: Programming Language :: Python :: 3.10
Classifier: Programming Language :: Python :: 3.11
Classifier: Programming Language :: Python :: 3.10
Classifier: Programming Language :: Python :: 3.8
Classifier: Programming Language :: Python :: 3.9
Classifier: Topic :: Internet :: WWW/HTTP
Requires-Dist: aiofiles (>=0.3.1)
Requires-Dist: ant-nest (>=1.0.1)
Requires-Dist: ipython (>=8.11.0)
Requires-Dist: prompt-toolkit (>=3.0.38)
Requires-Dist: rich (>=13.3.1)
Requires-Dist: tenacity (>=4.8.0)
Requires-Dist: tqdm (>=4.64.1)
Requires-Dist: typer (>=0.7.0)
Requires-Dist: typing_extensions (>=3.6)
Requires-Dist: ujson (>=1.3.4)
Project-URL: Repository, https://github.com/strongbugman/pikpak_cli
